simple_classproperty/__init__.py
simple_classproperty/classproperty_decorator.py
simple_classproperty/classproperty_meta.py
simple_classproperty/py.typed
simple_classproperty-4.0.2.dist-info/LICENSE
simple_classproperty-4.0.2.dist-info/METADATA
simple_classproperty-4.0.2.dist-info/WHEEL
simple_classproperty-4.0.2.dist-info/RECORD
