Metadata-Version: 2.1
Name: simple-classproperty
Version: 4.0.2
Summary: Provides a 'classproperty' decorator.
Home-page: https://github.com/mammo0/py-simple-classproperty
License: GPL-3.0-only
Author: Marc Ammon
Author-email: marc.ammon@hotmail.de
Requires-Python: >=3.8
Classifier: License :: OSI Approved :: GNU General Public License v3 (GPLv3)
Classifier: Operating System :: OS Independent
Classifier: Programming Language :: Python :: 3
Classifier: Programming Language :: Python :: 3.8
Classifier: Programming Language :: Python :: 3.9
Classifier: Programming Language :: Python :: 3.10
Classifier: Programming Language :: Python :: 3.11
